acccmip5/__init__.py
acccmip5/access_cm.py
acccmip5/cli.py
acccmip5/download_dat.py
acccmip5/utilities/CMIP5_database.py
acccmip5/utilities/__init__.py
acccmip5/utilities/c5db.py
acccmip5/utilities/checkers.py
acccmip5/utilities/util.py
acccmip5/utilities/data/__init__.py
acccmip5-1.0.2.dist-info/AUTHORS.rst
acccmip5-1.0.2.dist-info/LICENSE
acccmip5-1.0.2.dist-info/METADATA
acccmip5-1.0.2.dist-info/WHEEL
acccmip5-1.0.2.dist-info/entry_points.txt
acccmip5-1.0.2.dist-info/top_level.txt
acccmip5-1.0.2.dist-info/RECORD
