Metadata-Version: 2.1
Name: acccmip5
Version: 1.0.2
Summary: Package for accessing CMIP5 database in real-time
Home-page: https://github.com/TaufiqHassan/acccmip5
Author: Taufiq Hassan
Author-email: taufiq.hassanmozumder@email.ucr.edu
License: MIT
Platform: UNKNOWN
Classifier: License :: OSI Approved :: MIT License
Classifier: Natural Language :: English
Classifier: Programming Language :: Python :: 3.5
Classifier: Programming Language :: Python :: 3.6
Classifier: Programming Language :: Python :: 3.7
Requires-Dist: pandas
Requires-Dist: requests
Requires-Dist: setuptools
Requires-Dist: xlrd
